{
  "slug": "culver-emma-louise",
  "name": "Culver, Emma Louise",
  "extractedAt": "2026-01-16T03:08:00.000Z",
  "images": [],
  "keyDates": "1872: Born in Oct 1872 in Gaysville, Vermont. [Ref]\n\n1880: Emma L. was seven and living with her parents in Des Moines.\n\n1900: Louise was living with her parents in Orcas.\n\n1910: Louise and Cecil were living in Orcas and Cecil was a fruit farmer.\n\n1920: Louise and Cecil were living in Olga, San Juan, Washington and Cecil was a farmer.\n\n1930: Louise was a widow living in Olga.",
  "notes": "TBD\n\n· She married Cecil Swainson Willis. [Ref]\n\n· Cecil was born on 20 Jul 1873 [Ref] in England. [Ref, Jul 1873]\n\n· Cecil died between 1920 and 1930.",
  "immediateFamily": {
    "daughterOf": "George Nelson Culver and Diana Louise Aikens",
    "wifeOf": "Cecil Swainson Willis",
    "motherOf": "Cecil Culver Willis",
    "sisterOf": "Otis Henry Culver, Fred Nelson Culver, Inez Adel Culver"
  }
}
