{
  "slug": "johanson-helge",
  "displayName": "Helge Johanson",
  "sourceUrl": "https://sites.google.com/view/orcashistoryresearch/people/johanson-helge",

  "connectionToPtLawrence": null,

  "family": {
    "parents": "TBD",
    "spouses": "Mabel Florian Culver",
    "children": "Larry Johanson",
    "siblings": "TBD"
  },

  "keyDates": "TBD",

  "timeline": [],

  "biography": null,

  "miscellaneous": "Husband of Mabel Florian Culver (daughter of O.H. Culver).",

  "researchQuestions": [],

  "extractedAt": "2026-01-14",
  "notes": "Stub page - mostly TBD content"
}
